agentify/__init__.py
agentify/core/__init__.py
agentify/core/agent.py
agentify/core/callbacks.py
agentify/core/config.py
agentify/core/runnable.py
agentify/core/tool.py
agentify/extensions/__init__.py
agentify/extensions/prompts/__init__.py
agentify/extensions/prompts/assistant.py
agentify/extensions/tools/__init__.py
agentify/extensions/tools/calculator.py
agentify/extensions/tools/filesystem.py
agentify/extensions/tools/planning.py
agentify/extensions/tools/time.py
agentify/extensions/tools/weather.py
agentify/llm/__init__.py
agentify/llm/client.py
agentify/mcp/__init__.py
agentify/mcp/adapter.py
agentify/mcp/client.py
agentify/memory/__init__.py
agentify/memory/interfaces.py
agentify/memory/policies.py
agentify/memory/service.py
agentify/memory/stores/__init__.py
agentify/memory/stores/elastic_store.py
agentify/memory/stores/in_memory_store.py
agentify/memory/stores/redis_store.py
agentify/memory/stores/sqlite_store.py
agentify/multi_agent/__init__.py
agentify/multi_agent/hierarchical.py
agentify/multi_agent/pipeline.py
agentify/multi_agent/team.py
agentify/multi_agent/tool_wrapper.py
agentify/utils/__init__.py
agentify/utils/style.py
agentify_core-0.3.1.dist-info/licenses/LICENSE
agentify_core-0.3.1.dist-info/METADATA
agentify_core-0.3.1.dist-info/WHEEL
agentify_core-0.3.1.dist-info/top_level.txt
agentify_core-0.3.1.dist-info/RECORD
