Metadata-Version: 2.4
Name: agentify-core
Version: 0.3.1
Summary: Framework-agnostic AI agent library for building single and multi-agent systems
Author: Fabian M
Author-email: fabianmp_98@hotmail.com
License: MIT
Project-URL: Homepage, https://github.com/fa8i/Agentify
Project-URL: Repository, https://github.com/fa8i/Agentify
Project-URL: Bug Tracker, https://github.com/fa8i/Agentify/issues
Keywords: agentify,agentify-core,agent,multi-agent,ai,llm,openai,framework
Classifier: Development Status :: 3 - Alpha
Classifier: Intended Audience :: Developers
Classifier: License :: OSI Approved :: MIT License
Classifier: Operating System :: OS Independent
Classifier: Programming Language :: Python :: 3
Classifier: Programming Language :: Python :: 3.10
Classifier: Programming Language :: Python :: 3.11
Classifier: Programming Language :: Python :: 3.12
Classifier: Topic :: Software Development :: Libraries :: Python Modules
Classifier: Topic :: Scientific/Engineering :: Artificial Intelligence
Requires-Python: >=3.10
License-File: LICENSE
Requires-Dist: openai
Requires-Dist: python-dotenv
Requires-Dist: Pillow
Requires-Dist: jsonschema>=4.0.0
Provides-Extra: redis
Requires-Dist: redis>=4.0.0; extra == "redis"
Provides-Extra: elastic
Requires-Dist: elasticsearch>=8.0.0; extra == "elastic"
Provides-Extra: tools
Requires-Dist: requests>=2.25.0; extra == "tools"
Provides-Extra: mcp
Requires-Dist: mcp; extra == "mcp"
Provides-Extra: ui
Requires-Dist: gradio==5.49.1; extra == "ui"
Provides-Extra: all
Requires-Dist: redis>=4.0.0; extra == "all"
Requires-Dist: elasticsearch>=8.0.0; extra == "all"
Requires-Dist: requests>=2.25.0; extra == "all"
Requires-Dist: gradio==5.49.1; extra == "all"
Requires-Dist: mcp; extra == "all"
Provides-Extra: dev
Requires-Dist: pytest>=7.0.0; extra == "dev"
Requires-Dist: pytest-cov>=4.0.0; extra == "dev"
Requires-Dist: black>=22.0.0; extra == "dev"
Requires-Dist: flake8>=5.0.0; extra == "dev"
Requires-Dist: mypy>=1.0.0; extra == "dev"
Requires-Dist: twine>=4.0.0; extra == "dev"
Requires-Dist: build>=0.10.0; extra == "dev"
Dynamic: license-file
